pysiaalarm/__init__.py
pysiaalarm/account.py
pysiaalarm/base_client.py
pysiaalarm/base_server.py
pysiaalarm/const.py
pysiaalarm/errors.py
pysiaalarm/event.py
pysiaalarm/py.typed
pysiaalarm/aio/__init__.py
pysiaalarm/aio/client.py
pysiaalarm/aio/server.py
pysiaalarm/data/__init__.py
pysiaalarm/data/adm_mapping.json
pysiaalarm/data/data.py
pysiaalarm/data/sia_codes.json
pysiaalarm/data/xdata.json
pysiaalarm/sync/__init__.py
pysiaalarm/sync/client.py
pysiaalarm/sync/handler.py
pysiaalarm/sync/server.py
pysiaalarm/utils/__init__.py
pysiaalarm/utils/counter.py
pysiaalarm/utils/enums.py
pysiaalarm/utils/regexes.py
pysiaalarm-3.1.1.dist-info/AUTHORS.rst
pysiaalarm-3.1.1.dist-info/LICENSE.txt
pysiaalarm-3.1.1.dist-info/METADATA
pysiaalarm-3.1.1.dist-info/WHEEL
pysiaalarm-3.1.1.dist-info/top_level.txt
pysiaalarm-3.1.1.dist-info/RECORD
